{
  "articleID": 1883,
  "knowledgeCategoryID": 454,
  "sort": 6,
  "name": "Neto by Maropost Release Notes – 19 Jan 2021",
  "body": "[{\"type\":\"p\",\"children\":[{\"text\":\"Release Version\",\"bold\":true},{\"text\":\": 6.135\"}]},{\"type\":\"p\",\"children\":[{\"text\":\" \"}]},{\"type\":\"h2\",\"children\":[{\"text\":\"Minor Changes\",\"bold\":true}]},{\"type\":\"ul\",\"children\":[{\"type\":\"li\",\"children\":[{\"type\":\"lic\",\"children\":[{\"text\":\"Hunter Express shipping labels have been updated to the latest version.\"}]}]},{\"type\":\"li\",\"children\":[{\"type\":\"lic\",\"children\":[{\"text\":\"The Shipping Date Groups link has been added to the All settings & tools page. Date groups let you set specific days when orders aren't picked up or shipped, such as public or local holidays.\"}]}]}]},{\"type\":\"p\",\"children\":[{\"text\":\" \"}]},{\"type\":\"h2\",\"children\":[{\"text\":\"Bug Fixes\",\"bold\":true}]},{\"type\":\"ul\",\"children\":[{\"type\":\"li\",\"children\":[{\"text\":\"Fixed an issue where failed batch tasks would repeatedly send batch job error emails. A failure will now only send once.\"}]}]},{\"type\":\"p\",\"children\":[{\"text\":\" \"}]}]",
  "format": "rich2",
  "featured": false,
  "locale": "en",
  "status": "published",
  "foreignID": null,
  "dateUpdated": "2025-07-10T15:03:34+00:00",
  "_source_kb_id": 12,
  "_source_kb_name": "Neto Release Notes",
  "_sync_date": "2026-02-02T05:59:05.901791+00:00"
}