{
  "articleID": 2342,
  "knowledgeCategoryID": 491,
  "sort": 0,
  "name": "Inventory Page Overview",
  "body": "[{\"type\":\"p\",\"children\":[{\"text\":\"The \"},{\"text\":\"Inventory page\",\"bold\":true},{\"text\":\" offers a centralized view of all product SKUs and their current stock levels across multiple warehouses or fulfillment locations. This helps businesses \"},{\"text\":\"track availability\",\"bold\":true},{\"text\":\", \"},{\"text\":\"monitor stock movement\",\"bold\":true},{\"text\":\", and \"},{\"text\":\"manage reservations\",\"bold\":true},{\"text\":\" efficiently.\"}]},{\"type\":\"h2\",\"children\":[{\"text\":\"To access \"}]},{\"type\":\"p\",\"children\":[{\"text\":\"Go to Inventory >> Inventory\"}]},{\"type\":\"rich_embed_card\",\"children\":[{\"text\":\"\"}],\"dataSourceType\":\"image\",\"url\":\"https://us.v-cdn.net/6038474/uploads/MIMWL7RACY5Q/image.png\",\"embedData\":{\"url\":\"https://us.v-cdn.net/6038474/uploads/MIMWL7RACY5Q/image.png\",\"name\":\"image.png\",\"type\":\"image/png\",\"size\":1199685,\"width\":2880,\"height\":1618,\"displaySize\":\"large\",\"float\":\"none\",\"downloadUrl\":\"https://galaxy.maropost.com/api/v2/media/download-by-url?url=https%3A%2F%2Fus.v-cdn.net%2F6038474%2Fuploads%2FMIMWL7RACY5Q%2Fimage.png\",\"active\":true,\"mediaID\":1380,\"dateInserted\":\"2025-11-03T09:57:03+00:00\",\"insertUserID\":1178,\"foreignType\":\"embed\",\"foreignID\":\"1178\",\"embedType\":\"image\"}},{\"type\":\"p\",\"children\":[{\"text\":\" \"}]},{\"type\":\"p\",\"children\":[{\"text\":\"The inventory table displays the following columns for each product:\"}]},{\"type\":\"table\",\"children\":[{\"type\":\"tr\",\"children\":[{\"type\":\"th\",\"attributes\":{\"rowspan\":\"1\",\"colspan\":\"1\"},\"children\":[{\"type\":\"p\",\"children\":[{\"text\":\"Field\",\"bold\":true}]}]},{\"type\":\"th\",\"attributes\":{\"rowspan\":\"1\",\"colspan\":\"1\"},\"children\":[{\"type\":\"p\",\"children\":[{\"text\":\"Description\",\"bold\":true}]}]}]},{\"type\":\"tr\",\"children\":[{\"type\":\"td\",\"attributes\":{\"rowspan\":\"1\",\"colspan\":\"1\"},\"children\":[{\"type\":\"p\",\"children\":[{\"text\":\"Title\",\"bold\":true}]}]},{\"type\":\"td\",\"attributes\":{\"rowspan\":\"1\",\"colspan\":\"1\"},\"children\":[{\"type\":\"p\",\"children\":[{\"text\":\"The product or variant name, clickable to view more details\"}]}]}]},{\"type\":\"tr\",\"children\":[{\"type\":\"td\",\"attributes\":{\"rowspan\":\"1\",\"colspan\":\"1\"},\"children\":[{\"type\":\"p\",\"children\":[{\"text\":\"SKU\",\"bold\":true}]}]},{\"type\":\"td\",\"attributes\":{\"rowspan\":\"1\",\"colspan\":\"1\"},\"children\":[{\"type\":\"p\",\"children\":[{\"text\":\"Unique identifier of the item\"}]}]}]},{\"type\":\"tr\",\"children\":[{\"type\":\"td\",\"attributes\":{\"rowspan\":\"1\",\"colspan\":\"1\"},\"children\":[{\"type\":\"p\",\"children\":[{\"text\":\"Warehouse\",\"bold\":true}]}]},{\"type\":\"td\",\"attributes\":{\"rowspan\":\"1\",\"colspan\":\"1\"},\"children\":[{\"type\":\"p\",\"children\":[{\"text\":\"The location where this inventory is stored\"}]}]}]},{\"type\":\"tr\",\"children\":[{\"type\":\"td\",\"attributes\":{\"rowspan\":\"1\",\"colspan\":\"1\"},\"children\":[{\"type\":\"p\",\"children\":[{\"text\":\"Reserved\",\"bold\":true}]}]},{\"type\":\"td\",\"attributes\":{\"rowspan\":\"1\",\"colspan\":\"1\"},\"children\":[{\"type\":\"p\",\"children\":[{\"text\":\"Quantity held for pending or confirmed orders\"}]}]}]},{\"type\":\"tr\",\"children\":[{\"type\":\"td\",\"attributes\":{\"rowspan\":\"1\",\"colspan\":\"1\"},\"children\":[{\"type\":\"p\",\"children\":[{\"text\":\"Available\",\"bold\":true}]}]},{\"type\":\"td\",\"attributes\":{\"rowspan\":\"1\",\"colspan\":\"1\"},\"children\":[{\"type\":\"p\",\"children\":[{\"text\":\"Number of units available to sell\"}]}]}]},{\"type\":\"tr\",\"children\":[{\"type\":\"td\",\"attributes\":{\"rowspan\":\"1\",\"colspan\":\"1\"},\"children\":[{\"type\":\"p\",\"children\":[{\"text\":\"In Stock\",\"bold\":true}]}]},{\"type\":\"td\",\"attributes\":{\"rowspan\":\"1\",\"colspan\":\"1\"},\"children\":[{\"type\":\"p\",\"children\":[{\"text\":\"Total quantity in the system (Reserved + Available)\"}]}]}]},{\"type\":\"tr\",\"children\":[{\"type\":\"td\",\"attributes\":{\"rowspan\":\"1\",\"colspan\":\"1\"},\"children\":[{\"type\":\"p\",\"children\":[{\"text\":\"Actions\",\"bold\":true}]}]},{\"type\":\"td\",\"attributes\":{\"rowspan\":\"1\",\"colspan\":\"1\"},\"children\":[{\"type\":\"p\",\"children\":[{\"text\":\"A three-dot menu (\"},{\"text\":\"⋮\",\"code\":true},{\"text\":\") offering management options\"}]}]}]}],\"id\":\"table-0-6\",\"colSizes\":[300,300]},{\"type\":\"p\",\"children\":[{\"text\":\"\"}]},{\"type\":\"h2\",\"children\":[{\"text\":\"Location Filter\"}]},{\"type\":\"p\",\"children\":[{\"text\":\"Located in the top-right corner, the \"},{\"text\":\"Location dropdown\",\"bold\":true},{\"text\":\" allows users to filter inventory data by specific warehouses.\\nThis is especially useful for:\"}]},{\"type\":\"ul\",\"children\":[{\"type\":\"li\",\"children\":[{\"type\":\"lic\",\"children\":[{\"text\":\"Viewing stock levels at individual locations\"}]}]},{\"type\":\"li\",\"children\":[{\"type\":\"lic\",\"children\":[{\"text\":\"Ensuring that local stores or fulfillment centers have sufficient inventory\"}]}]},{\"type\":\"li\",\"children\":[{\"type\":\"lic\",\"children\":[{\"text\":\"Making regional stock decisions without affecting global data\"}]}]}]},{\"type\":\"p\",\"children\":[{\"text\":\"When a location is selected, the table updates to reflect \"},{\"text\":\"only the stock associated with that location\",\"bold\":true},{\"text\":\".\"}]},{\"type\":\"rich_embed_card\",\"children\":[{\"text\":\"\"}],\"dataSourceType\":\"image\",\"url\":\"https://us.v-cdn.net/6038474/uploads/CR7GV0646W3U/image.png\",\"embedData\":{\"url\":\"https://us.v-cdn.net/6038474/uploads/CR7GV0646W3U/image.png\",\"name\":\"image.png\",\"type\":\"image/png\",\"size\":2350813,\"width\":2560,\"height\":1438,\"displaySize\":\"large\",\"float\":\"none\",\"downloadUrl\":\"https://galaxy.maropost.com/api/v2/media/download-by-url?url=https%3A%2F%2Fus.v-cdn.net%2F6038474%2Fuploads%2FCR7GV0646W3U%2Fimage.png\",\"active\":true,\"mediaID\":1382,\"dateInserted\":\"2025-11-03T09:58:25+00:00\",\"insertUserID\":1178,\"foreignType\":\"embed\",\"foreignID\":\"1178\",\"embedType\":\"image\"}},{\"type\":\"p\",\"children\":[{\"text\":\"\"}]},{\"type\":\"h2\",\"children\":[{\"text\":\"Inventory Details Page\"}]},{\"type\":\"p\",\"children\":[{\"text\":\"You can access the \"},{\"text\":\"Inventory Details Page\",\"bold\":true},{\"text\":\" in two ways:\"}]},{\"type\":\"ul\",\"children\":[{\"type\":\"li\",\"children\":[{\"type\":\"lic\",\"children\":[{\"text\":\"By \"},{\"text\":\"clicking the product title link\",\"bold\":true},{\"text\":\" on the Inventory table.\"}]}]},{\"type\":\"li\",\"children\":[{\"type\":\"lic\",\"children\":[{\"text\":\"By selecting \"},{\"text\":\"‘Edit’\",\"bold\":true},{\"text\":\" from the \"},{\"text\":\"3-dot (⋮) Actions menu\",\"bold\":true},{\"text\":\" next to the item.\"}]}]}]},{\"type\":\"p\",\"children\":[{\"text\":\"At the top of the page, you'll see a summary of the specific product variant you're editing. This helps you quickly confirm which product variant you're managing. This includes:\"}]},{\"type\":\"ul\",\"children\":[{\"type\":\"li\",\"children\":[{\"type\":\"lic\",\"children\":[{\"text\":\"SKU\",\"bold\":true},{\"text\":\": Unique identifier for the variant (e.g., NK1512_210)\"}]}]},{\"type\":\"li\",\"children\":[{\"type\":\"lic\",\"children\":[{\"text\":\"Size\",\"bold\":true},{\"text\":\": Variant size label (e.g., XS)\"}]}]}]},{\"type\":\"rich_embed_card\",\"children\":[{\"text\":\"\"}],\"dataSourceType\":\"image\",\"url\":\"https://us.v-cdn.net/6038474/uploads/HEQ2OEL8F77P/image.png\",\"embedData\":{\"url\":\"https://us.v-cdn.net/6038474/uploads/HEQ2OEL8F77P/image.png\",\"name\":\"image.png\",\"type\":\"image/png\",\"size\":2315578,\"width\":2560,\"height\":1440,\"displaySize\":\"large\",\"float\":\"none\",\"downloadUrl\":\"https://galaxy.maropost.com/api/v2/media/download-by-url?url=https%3A%2F%2Fus.v-cdn.net%2F6038474%2Fuploads%2FHEQ2OEL8F77P%2Fimage.png\",\"active\":true,\"mediaID\":1383,\"dateInserted\":\"2025-11-03T09:59:05+00:00\",\"insertUserID\":1178,\"foreignType\":\"embed\",\"foreignID\":\"1178\",\"embedType\":\"image\"}},{\"type\":\"h2\",\"children\":[{\"text\":\"\\n\"},{\"text\":\"Associated Variant Panel\",\"bold\":true}]},{\"type\":\"p\",\"children\":[{\"text\":\"On the right-hand side, under \"},{\"text\":\"Associated Variant\",\"bold\":true},{\"text\":\", the currently selected variant (e.g., XS) is shown. You can click on this option to view and edit other variants. \"}]},{\"type\":\"rich_embed_card\",\"children\":[{\"text\":\"\"}],\"dataSourceType\":\"image\",\"url\":\"https://us.v-cdn.net/6038474/uploads/3DAGY2PD6NTY/image.png\",\"embedData\":{\"url\":\"https://us.v-cdn.net/6038474/uploads/3DAGY2PD6NTY/image.png\",\"name\":\"image.png\",\"type\":\"image/png\",\"size\":2328211,\"width\":2560,\"height\":1438,\"displaySize\":\"large\",\"float\":\"none\",\"downloadUrl\":\"https://galaxy.maropost.com/api/v2/media/download-by-url?url=https%3A%2F%2Fus.v-cdn.net%2F6038474%2Fuploads%2F3DAGY2PD6NTY%2Fimage.png\",\"active\":true,\"mediaID\":1384,\"dateInserted\":\"2025-11-03T09:59:41+00:00\",\"insertUserID\":1178,\"foreignType\":\"embed\",\"foreignID\":\"1178\",\"embedType\":\"image\"}},{\"type\":\"p\",\"children\":[{\"text\":\"\"}]},{\"type\":\"h2\",\"children\":[{\"text\":\"Inventory Section\",\"bold\":true}]},{\"type\":\"p\",\"children\":[{\"text\":\"This section allows you to manage barcode identifiers and backorder settings:\"}]},{\"type\":\"ul\",\"children\":[{\"type\":\"li\",\"children\":[{\"type\":\"lic\",\"children\":[{\"text\":\"EAN/UPC/Barcode\",\"bold\":true},{\"text\":\" fields can be filled in for product tracking.\"}]}]},{\"type\":\"li\",\"children\":[{\"type\":\"lic\",\"children\":[{\"text\":\"Manage inventory \",\"bold\":true},{\"text\":\"toggle\"},{\"bold\":true,\"text\":\": \"},{\"text\":\"When enabled, Maropost Commerce Cloud automatically adjusts stock levels based on orders, returns, and manual reservations.\"}]}]},{\"type\":\"li\",\"children\":[{\"type\":\"lic\",\"children\":[{\"text\":\"Allow backorders\",\"bold\":true},{\"text\":\" toggle: When enabled, this allows customers to purchase the product even when it’s out of stock.\"}]}]}]},{\"type\":\"p\",\"children\":[{\"text\":\"This helps manage fulfillment flexibility.\"}]},{\"type\":\"rich_embed_card\",\"children\":[{\"text\":\"\"}],\"dataSourceType\":\"image\",\"url\":\"https://us.v-cdn.net/6038474/uploads/Z9QQYTMR0YRK/image.png\",\"embedData\":{\"url\":\"https://us.v-cdn.net/6038474/uploads/Z9QQYTMR0YRK/image.png\",\"name\":\"image.png\",\"type\":\"image/png\",\"size\":1646174,\"width\":2560,\"height\":1438,\"displaySize\":\"large\",\"float\":\"none\",\"downloadUrl\":\"https://galaxy.maropost.com/api/v2/media/download-by-url?url=https%3A%2F%2Fus.v-cdn.net%2F6038474%2Fuploads%2FZ9QQYTMR0YRK%2Fimage.png\",\"active\":true,\"mediaID\":1385,\"dateInserted\":\"2025-11-03T10:00:12+00:00\",\"insertUserID\":1178,\"foreignType\":\"embed\",\"foreignID\":\"1178\",\"embedType\":\"image\"}},{\"type\":\"p\",\"children\":[{\"text\":\" \"}]},{\"type\":\"h2\",\"children\":[{\"text\":\"Attributes Panel\",\"bold\":true}]},{\"type\":\"p\",\"children\":[{\"text\":\"The Attributes section contains physical and identification details about the product:\"}]},{\"type\":\"ul\",\"children\":[{\"type\":\"li\",\"children\":[{\"type\":\"lic\",\"children\":[{\"text\":\"Height, Width, Length, Weight\",\"bold\":true}]}]},{\"type\":\"li\",\"children\":[{\"type\":\"lic\",\"children\":[{\"text\":\"MID Code\",\"bold\":true}]}]},{\"type\":\"li\",\"children\":[{\"type\":\"lic\",\"children\":[{\"text\":\"HS Code\",\"bold\":true},{\"text\":\" (e.g., 62024090)\"}]}]},{\"type\":\"li\",\"children\":[{\"type\":\"lic\",\"children\":[{\"text\":\"Country of Origin\",\"bold\":true},{\"text\":\" (e.g., Australia)\"}]}]}]},{\"type\":\"p\",\"children\":[{\"text\":\"These attributes are crucial for shipping, customs, and international compliance. You add/edit these details by click the pencil option. \"}]},{\"type\":\"rich_embed_card\",\"children\":[{\"text\":\"\"}],\"dataSourceType\":\"image\",\"url\":\"https://us.v-cdn.net/6038474/uploads/LOO0MGWDJ268/image.png\",\"embedData\":{\"url\":\"https://us.v-cdn.net/6038474/uploads/LOO0MGWDJ268/image.png\",\"name\":\"image.png\",\"type\":\"image/png\",\"size\":2327797,\"width\":2560,\"height\":1438,\"displaySize\":\"large\",\"float\":\"none\",\"downloadUrl\":\"https://galaxy.maropost.com/api/v2/media/download-by-url?url=https%3A%2F%2Fus.v-cdn.net%2F6038474%2Fuploads%2FLOO0MGWDJ268%2Fimage.png\",\"active\":true,\"mediaID\":1386,\"dateInserted\":\"2025-11-03T10:00:48+00:00\",\"insertUserID\":1178,\"foreignType\":\"embed\",\"foreignID\":\"1178\",\"embedType\":\"image\"}},{\"type\":\"p\",\"children\":[{\"text\":\" \"}]},{\"type\":\"h2\",\"children\":[{\"text\":\"Locations Section\",\"bold\":true}]},{\"type\":\"p\",\"children\":[{\"text\":\"This section displays the stock distribution across locations. It provides a real-time snapshot of inventory across fulfillment centers.\"}]},{\"type\":\"ul\",\"children\":[{\"type\":\"li\",\"children\":[{\"type\":\"lic\",\"children\":[{\"text\":\"Reserved\",\"bold\":true},{\"text\":\": Quantity currently reserved for orders.\"}]}]},{\"type\":\"li\",\"children\":[{\"type\":\"lic\",\"children\":[{\"text\":\"In-stock\",\"bold\":true},{\"text\":\": Quantity physically available in inventory.\"}]}]},{\"type\":\"li\",\"children\":[{\"type\":\"lic\",\"children\":[{\"text\":\"Available\",\"bold\":true},{\"text\":\": Quantity available for sale (excluding reserved stock).\"}]}]}]},{\"type\":\"rich_embed_card\",\"children\":[{\"text\":\"\"}],\"dataSourceType\":\"image\",\"url\":\"https://us.v-cdn.net/6038474/uploads/6ZX0ZBOAG8RX/image.png\",\"embedData\":{\"url\":\"https://us.v-cdn.net/6038474/uploads/6ZX0ZBOAG8RX/image.png\",\"name\":\"image.png\",\"type\":\"image/png\",\"size\":349828,\"width\":2560,\"height\":1435,\"displaySize\":\"large\",\"float\":\"none\",\"downloadUrl\":\"https://galaxy.maropost.com/api/v2/media/download-by-url?url=https%3A%2F%2Fus.v-cdn.net%2F6038474%2Fuploads%2F6ZX0ZBOAG8RX%2Fimage.png\",\"active\":true,\"mediaID\":1387,\"dateInserted\":\"2025-11-03T10:01:28+00:00\",\"insertUserID\":1178,\"foreignType\":\"embed\",\"foreignID\":\"1178\",\"embedType\":\"image\"}},{\"type\":\"p\",\"children\":[{\"text\":\"Clicking on the \"},{\"text\":\"3-dot menu\",\"bold\":true},{\"text\":\" in this section opens a dropdown where you can select \"},{\"text\":\"Manage Locations\",\"bold\":true},{\"text\":\". Once inside the \"},{\"text\":\"Manage Locations\",\"bold\":true},{\"text\":\" modal, you'll see a list of all locations that stock the selected variant. You can:\"}]},{\"type\":\"ul\",\"children\":[{\"type\":\"li\",\"children\":[{\"type\":\"lic\",\"children\":[{\"text\":\"Select or deselect locations to see the available quantity for this variant.\"}]}]},{\"type\":\"li\",\"children\":[{\"type\":\"lic\",\"children\":[{\"text\":\"Click \"},{\"text\":\"Save\",\"bold\":true},{\"text\":\" to apply the changes.\"}]}]}]},{\"type\":\"p\",\"children\":[{\"text\":\"Once, you have selected the location, you will see the available units at that location and make reservations. \"}]},{\"type\":\"rich_embed_card\",\"children\":[{\"text\":\"\"}],\"dataSourceType\":\"url\",\"url\":\"https://youtu.be/SxoF8xN5Rhw\",\"embedData\":{\"height\":113,\"width\":200,\"photoUrl\":\"https://i.ytimg.com/vi/SxoF8xN5Rhw/hqdefault.jpg\",\"videoID\":\"SxoF8xN5Rhw\",\"showRelated\":false,\"url\":\"https://youtu.be/SxoF8xN5Rhw\",\"embedType\":\"youtube\",\"name\":\"Inventory Page Overview\",\"frameSrc\":\"https://www.youtube.com/embed/SxoF8xN5Rhw?feature=oembed&autoplay=1\"}},{\"type\":\"p\",\"children\":[{\"text\":\"\"}]}]",
  "format": "rich2",
  "featured": false,
  "locale": "en",
  "status": "published",
  "foreignID": null,
  "dateUpdated": "2025-11-03T11:04:47+00:00",
  "_source_kb_id": 14,
  "_source_kb_name": "Commerce Cloud",
  "_sync_date": "2026-02-02T06:00:02.455918+00:00"
}